functionmonitor/__init__.py
functionmonitor/core.py
functionmonitor-0.1.7.dist-info/LICENSE
functionmonitor-0.1.7.dist-info/METADATA
functionmonitor-0.1.7.dist-info/WHEEL
functionmonitor-0.1.7.dist-info/top_level.txt
functionmonitor-0.1.7.dist-info/RECORD
