Metadata-Version: 2.1
Name: functionmonitor
Version: 0.1.7
Summary: A tool for monitoring and managing asynchronous function execution.
Home-page: https://github.com/djchou/functionmonitor
Author: Dennis Chou
Author-email: dennischou@gmail.com
Classifier: Programming Language :: Python :: 3
Classifier: License :: OSI Approved :: MIT License
Classifier: Operating System :: OS Independent
Requires-Python: >=3.6
License-File: LICENSE
Requires-Dist: IPython
